Metadata-Version: 2.1
Name: dlmatpower
Version: 0.0.1.post1
Summary: Make download MATPOWER easier from pip
Home-page: https://gitlab.com/yasirroni/dlmatpower
Author: Muhammad Yasirroni
Author-email: muhammadyasirroni@gmail.com
License: UNKNOWN
Platform: UNKNOWN
Classifier: Programming Language :: Python
Classifier: Topic :: Scientific/Engineering
License-File: LICENSE
